ws_proxy/__init__.py
ws_proxy/connection.py
ws_proxy/constants.py
ws_proxy/log.py
ws_proxy/server.py
ws_proxy/utils.py
ws_proxy-0.2.8.data/scripts/ws_proxy
ws_proxy-0.2.8.dist-info/METADATA
ws_proxy-0.2.8.dist-info/WHEEL
ws_proxy-0.2.8.dist-info/top_level.txt
ws_proxy-0.2.8.dist-info/RECORD
