Metadata-Version: 2.1
Name: ws-proxy
Version: 0.2.8
Summary: tcp's websocket proxy
Home-page: https://github.com/dantezhu/ws_proxy
Author: dantezhu
Author-email: dantezhu <zny2008@gmail.com>
License: MIT
Project-URL: Homepage, https://github.com/dantezhu/ws_proxy
Platform: any
Requires-Dist: gevent-websocket
Requires-Dist: netkit
